LICENSE.txt
MANIFEST.in
README.rst
setup.py
tools.py
bendan/bendanya.py
bendanya.egg-info/PKG-INFO
bendanya.egg-info/SOURCES.txt
bendanya.egg-info/dependency_links.txt
bendanya.egg-info/top_level.txt